{
    "instrument": "flute",
    "beat": 4,
    "sustain": true,
    "transpose": 5,
    "notes": [
        "||1",
        "||2",
        "||3",
        "||4",
        "||5",
        "| 6", "r 2b", { "dynamic": 1, "sustain": -3 }, "d 2b", "cs 2b", "c 2b",
        "| 7", { "transpose": -5, "sustain": true, "dynamic": 2, "sustainDynamic": 1 }, "e 4b 2b.", "e",
        "| 8", "f 2b.", "f", "e 2b", "r 2b",
        "| 9", "e 2b.", "e", "e", "e", "e", "e",
        "| 10", "f 4b", "e 2b", "r 2b",
        "||11",
        "||12",
        "||13",
        "||14",
        "||15",
        "| 16", "r 2b", { "transpose": 0, "sustain": -3, "dynamic": 1 }, "b_ 2b", "as_ 2b", "a_ 2b",
        "| 17", { "transpose": -5, "sustain": true, "dynamic": 2 }, "c 4b 2b.", "c",
        "| 18", "d 2b.", "d", "c", "cs", "d", "e",
        "| 19", "f 2b", "f", "f", "f 2b", "f 2b",
        "| 20", "g 4b", { "name": "f 2b", "sustain": -3 }, "f 2b 2b.",
        "f", "e 2b", "r 2b",
        "| 22", "e 2b.", "e", "d 2b", "r 2b",
        "| 23", "d 2b.", "d", "c", "c", "d", "d",
        "| 24", "d 2b", "c 2b", "b_ 4b",
        { "beat": 8 },
        "| 25", { "transpose": 0, "dynamic": 1, "sustainDynamic": null }, "b_ 4b",
        "| 26", { "dynamic": 2 }, "cs 4b",
        "| 27", "d 4b",
        "| 28", "bb_ 2b", "ab_ 2b",
        "| 29", "bb_ 4b",
        "| 30", "bs_ 4b",
        "| 31", "cs 4b",
        "| 32", "a_ 4b",
        "| 33", "a_ 4b",
        "| 34", "b_ 4b",
        "| 35", "c 2b", "ab_ 2b",
        "| 36", "as_ 4b",
        "| 37", "b_ 2b", "c", "g_",
        "| 38", "g_ 4b",
        "| 39", "g_ 4b",
        { "beat": 16 },
        "| 40", { "dynamic": 1 }, "g_"
    ]
}